discogs/__init__.py
discogs/chunker.py
discogs/config.py
discogs/converter.py
discogs/deleter.py
discogs/downloader.py
discogs/extractor.py
discogs/main.py
discogs/scraper.py
discogs/selector.py
discogs/utils.py
discogsdataprocessorcli-1.6.dist-info/METADATA
discogsdataprocessorcli-1.6.dist-info/WHEEL
discogsdataprocessorcli-1.6.dist-info/entry_points.txt
discogsdataprocessorcli-1.6.dist-info/top_level.txt
discogsdataprocessorcli-1.6.dist-info/RECORD
