Metadata-Version: 2.4
Name: DiscogsDataProcessorCLI
Version: 1.6
Summary: A CLI to download, extract and convert Discogs data dumps
Home-page: https://github.com/ofurkancoban/DiscogsCLI
Author: Furkan Çoban
Author-email: ofurkancoban@gmail.com
License: MIT
Classifier: Programming Language :: Python :: 3
Classifier: License :: OSI Approved :: MIT License
Classifier: Operating System :: OS Independent
Requires-Python: >=3.8
Requires-Dist: rich
Requires-Dist: pandas
Requires-Dist: typer
